pulsar/__init__.py
pulsar/AutoRead.py
pulsar/Stream.py
eyecu_pulsar-0.1.8.dist-info/WHEEL
eyecu_pulsar-0.1.8.dist-info/METADATA
eyecu_pulsar-0.1.8.dist-info/RECORD
