Metadata-Version: 2.1
Name: eyecu-pulsar
Version: 0.1.8
Summary: RTSP Sync Library
Home-page: https://github.com/eyecuvision/pulsar
License: MIT
Keywords: Video Streaming,rtsp,Open CV
Author: Oguz Vuruskaner
Author-email: ovuruska@outlook.com
Requires-Python: >=3.6,<4.0
Classifier: License :: OSI Approved :: MIT License
Classifier: Programming Language :: Python :: 3
Classifier: Programming Language :: Python :: 3.6
Classifier: Programming Language :: Python :: 3.7
Classifier: Programming Language :: Python :: 3.8
Classifier: Programming Language :: Python :: 3.9
Project-URL: Repository, https://github.com/eyecuvision/pulsar
